README.txt
setup.py
Products/__init__.py
Products.sampleremember.egg-info/PKG-INFO
Products.sampleremember.egg-info/SOURCES.txt
Products.sampleremember.egg-info/dependency_links.txt
Products.sampleremember.egg-info/entry_points.txt
Products.sampleremember.egg-info/namespace_packages.txt
Products.sampleremember.egg-info/not-zip-safe
Products.sampleremember.egg-info/requires.txt
Products.sampleremember.egg-info/top_level.txt
Products/sampleremember/README.txt
Products/sampleremember/__init__.py
Products/sampleremember/config.py
Products/sampleremember/permissions.py
Products/sampleremember/setuphandlers.py
Products/sampleremember/version.txt
Products/sampleremember/content/__init__.py
Products/sampleremember/content/sampleremember.py
Products/sampleremember/profiles/default/archetype_tool.xml
Products/sampleremember/profiles/default/import_steps.xml
Products/sampleremember/profiles/default/membership_properties.xml
Products/sampleremember/profiles/default/membrane_tool.xml
Products/sampleremember/profiles/default/remember-setup-plugins.txt
Products/sampleremember/profiles/default/skins.xml
Products/sampleremember/profiles/default/types.xml
Products/sampleremember/profiles/default/workflows.xml
Products/sampleremember/profiles/default/types/MemberDataContainer.xml
Products/sampleremember/profiles/default/types/SampleRemember.xml
Products/sampleremember/tests/__init__.py
Products/sampleremember/tests/base.py
Products/sampleremember/tests/test_sampleremember.py
docs/HISTORY.txt
docs/TODO.txt