Metadata-Version: 1.0
Name: Products.sampleremember
Version: 1.1b2
Summary: Sample remember based custom member implementation
Home-page: http://plone.org/products/remember
Author: Rob Miller
Author-email: robm@openplans.org
License: GPL
Platform: UNKNOWN
Classifier: Programming Language :: Python
Classifier: Topic :: Software Development :: Libraries :: Python Modules
